pyVig/__init__.py
pyVig/cablings.py
pyVig/common.py
pyVig/database.py
pyVig/devices.py
pyVig/entities.py
pyVig/general.py
pyVig/gui.py
pyVig/maths.py
pyVig/oper.py
pyVig/pyVig.py
pyVig/static.py
pyVig/stencils.py
pyVig/visio.py
pyVig/forms/__init__.py
pyVig/forms/custom.py
pyVig/forms/input_data - bkp..py
pyVig/forms/input_data.py
pyVig/forms/options.py
pyVig-0.1.1.dist-info/LICENSE
pyVig-0.1.1.dist-info/METADATA
pyVig-0.1.1.dist-info/WHEEL
pyVig-0.1.1.dist-info/top_level.txt
pyVig-0.1.1.dist-info/RECORD
